{
    "repositories": [
        {
            "id": 402,
            "name": "https://github.com/apache/avro.git",
            "first_commit": 1239300811000,
            "last_commit": 1391629839000,
            "developers": [
                {
                    "id": 6308,
                    "name": "Thiruvalluvan M. G",
                    "email": "thiru@apache.org",
                    "commits": 30
                },
                {
                    "id": 6317,
                    "name": "Miki Tebeka",
                    "email": "tebeka@apache.org",
                    "commits": 5
                },
                {
                    "id": 6323,
                    "name": "Bruce Mitchener Jr",
                    "email": "brucem@apache.org",
                    "commits": 2
                },
                {
                    "id": 6329,
                    "name": "Doug Cutting",
                    "email": "cutting@apache.org",
                    "commits": 239
                },
                {
                    "id": 6486,
                    "name": "Philip Zeyliger",
                    "email": "philz@apache.org",
                    "commits": 3
                },
                {
                    "id": 6493,
                    "name": "James Baldassari",
                    "email": "jbaldassari@apache.org",
                    "commits": 7
                },
                {
                    "id": 6505,
                    "name": "Douglas Adam Creager",
                    "email": "dcreager@apache.org",
                    "commits": 47
                },
                {
                    "id": 6512,
                    "name": "Thomas White",
                    "email": "tomwhite@apache.org",
                    "commits": 13
                },
                {
                    "id": 6528,
                    "name": "Scott Carey",
                    "email": "scottcarey@apache.org",
                    "commits": 13
                },
                {
                    "id": 6542,
                    "name": "Martin Kleppmann",
                    "email": "martinkl@apache.org",
                    "commits": 4
                }
            ]
        }
    ],
    "domain_aptitudes": [
        {
            "id": 117619,
            "name": "web",
            "desc": "Compétences relatives à l'environnement Web",
            "concrete_aptitudes": [
                {
                    "id": 3432,
                    "name": "js",
                    "desc": "Edition de fichiers Javascript"
                },
                {
                    "id": 110999,
                    "name": "php",
                    "desc": "Edition de fichiers Php"
                },
                {
                    "id": 98850,
                    "name": "css",
                    "desc": "Edition de fichiers CSS"
                },
                {
                    "id": 3213258,
                    "name": "html",
                    "desc": "Edition de fichiers HTML"
                }
            ]
        },
        {
            "id": 3254849,
            "name": "java",
            "desc": "Compétences relatives à l'environnement Java",
            "concrete_aptitudes": [
                {
                    "id": -843576936,
                    "name": "java_file",
                    "desc": "Edition de fichiers Java"
                }
            ]
        }
    ],
    "aptitude_expressions": [
        {
            "id_domain_aptitude": 117619,
            "expressions": [
                {
                    "id_concrete_aptitude": 3432,
                    "concrete_expressions": [
                        {
                            "repo": 402,
                            "dev": 6329,
                            "scores_times": [
                                "3_1349738767"
                            ]
                        }
                    ]
                },
                {
                    "id_concrete_aptitude": 110999,
                    "concrete_expressions": [
                        {
                            "repo": 402,
                            "dev": 6329,
                            "scores_times": [
                                "1_1337377110",
                                "1_1386889600"
                            ]
                        },
                        {
                            "repo": 402,
                            "dev": 6542,
                            "scores_times": [
                                "1_1365828206"
                            ]
                        }
                    ]
                },
                {
                    "id_concrete_aptitude": 98850,
                    "concrete_expressions": [
                        {
                            "repo": 402,
                            "dev": 6329,
                            "scores_times": [
                                "1_1347399356"
                            ]
                        }
                    ]
                },
                {
                    "id_concrete_aptitude": 3213258,
                    "concrete_expressions": [
                        {
                            "repo": 402,
                            "dev": 6329,
                            "scores_times": [
                                "1_1331154093",
                                "1_1342119805",
                                "3_1347399356",
                                "1_1354142554",
                                "1_1364419998",
                                "1_1375917418",
                                "1_1389309212"
                            ]
                        },
                        {
                            "repo": 402,
                            "dev": 6542,
                            "scores_times": [
                                "1_1366897861"
                            ]
                        }
                    ]
                }
            ]
        },
        {
            "id_domain_aptitude": 3254849,
            "expressions": [
                {
                    "id_concrete_aptitude": -843576936,
                    "concrete_expressions": [
                        {
                            "repo": 402,
                            "dev": 6308,
                            "scores_times": [
                                "1_1334229881",
                                "1_1336548947",
                                "2_1336759645"
                            ]
                        },
                        {
                            "repo": 402,
                            "dev": 6329,
                            "scores_times": [
                                "3_1327361199",
                                "2_1327361511",
                                "6_1328652941",
                                "2_1328653336",
                                "1_1328654458",
                                "3_1328654974",
                                "4_1328739230",
                                "5_1328746522",
                                "2_1330725020",
                                "1_1330726170",
                                "4_1331154093",
                                "3_1331939528",
                                "44_1334343792",
                                "1_1337203456",
                                "2_1337204842",
                                "4_1337205466",
                                "9_1337284249",
                                "1_1337285767",
                                "6_1337289163",
                                "2_1337289440",
                                "2_1337289784",
                                "1_1337293823",
                                "2_1337376550",
                                "3_1337633359",
                                "2_1337638455",
                                "2_1337804924",
                                "2_1339101704",
                                "43_1339451510",
                                "3_1339530389",
                                "1_1339530512",
                                "3_1339784738",
                                "6_1339795752",
                                "2_1341267163",
                                "2_1341524507",
                                "2_1342733100",
                                "10_1343855670",
                                "2_1347301908",
                                "1_1347320398",
                                "5_1347320425",
                                "44_1347399356",
                                "1_1347403078",
                                "2_1347493995",
                                "2_1347566687",
                                "2_1347568488",
                                "2_1347579610",
                                "2_1347912982",
                                "8_1347914570",
                                "1_1348521160",
                                "3_1348521779",
                                "5_1351791732",
                                "3_1352139725",
                                "2_1352926803",
                                "7_1352935289",
                                "2_1353107773",
                                "5_1353358629",
                                "4_1353536982",
                                "3_1353538648",
                                "2_1354142308",
                                "2_1354143365",
                                "6_1354226876",
                                "1_1355960287",
                                "2_1356036769",
                                "2_1358195359",
                                "2_1358457105",
                                "9_1358537674",
                                "6_1358543713",
                                "2_1358544124",
                                "3_1358544775",
                                "2_1358545146",
                                "2_1359064994",
                                "1_1360015125",
                                "6_1360016018",
                                "3_1360075637",
                                "2_1360256810",
                                "4_1360369325",
                                "2_1360698156",
                                "3_1360708045",
                                "10_1360711374",
                                "2_1360711690",
                                "3_1360874869",
                                "12_1360877365",
                                "4_1360878185",
                                "3_1360880778",
                                "2_1361212069",
                                "14_1361294122",
                                "2_1361480910",
                                "13_1364419998",
                                "5_1364427750",
                                "2_1366154756",
                                "2_1366660219",
                                "9_1366660782",
                                "3_1366736868",
                                "2_1366737083",
                                "5_1366748155",
                                "4_1367014336",
                                "5_1368034551",
                                "5_1368132906",
                                "3_1368133245",
                                "2_1368133487",
                                "7_1368137716",
                                "1_1368725633",
                                "1_1372787137",
                                "1_1372788011",
                                "7_1373407063",
                                "2_1373474406",
                                "3_1375903377",
                                "3_1375904862",
                                "17_1375917418",
                                "23_1375918026",
                                "2_1377030373",
                                "2_1378328397",
                                "1_1378931197",
                                "2_1380312775",
                                "3_1382739223",
                                "3_1383693276",
                                "2_1383781642",
                                "4_1383851349",
                                "13_1384152882",
                                "1_1385064552",
                                "4_1386796599",
                                "1_1386889600",
                                "4_1386896332",
                                "3_1386977576",
                                "6_1386978622",
                                "7_1387225838",
                                "2_1387226539",
                                "1_1387485185",
                                "2_1387486726",
                                "1_1389051217",
                                "7_1389132634",
                                "3_1389204258",
                                "8_1389288290",
                                "3_1389297110",
                                "22_1389309212",
                                "2_1389310448",
                                "2_1390860567",
                                "1_1390948658",
                                "7_1391556842",
                                "2_1391558997",
                                "1_1391629839"
                            ]
                        },
                        {
                            "repo": 402,
                            "dev": 6486,
                            "scores_times": [
                                "3_1360522908"
                            ]
                        },
                        {
                            "repo": 402,
                            "dev": 6493,
                            "scores_times": [
                                "1_1326814038",
                                "1_1326829342",
                                "2_1328599435",
                                "1_1328671471",
                                "2_1328672522",
                                "1_1373849608"
                            ]
                        },
                        {
                            "repo": 402,
                            "dev": 6505,
                            "scores_times": [
                                "2_1327596451"
                            ]
                        },
                        {
                            "repo": 402,
                            "dev": 6512,
                            "scores_times": [
                                "2_1347363117",
                                "2_1347364124",
                                "2_1347437948",
                                "3_1348752347",
                                "2_1352457981",
                                "2_1352458587",
                                "2_1352460330",
                                "2_1352800528",
                                "3_1355941932",
                                "6_1367235477"
                            ]
                        },
                        {
                            "repo": 402,
                            "dev": 6528,
                            "scores_times": [
                                "1_1328642709",
                                "3_1328731704",
                                "1_1330123412",
                                "15_1367338706",
                                "2_1367456507",
                                "3_1368651611",
                                "4_1375049412",
                                "1_1375237850"
                            ]
                        },
                        {
                            "repo": 402,
                            "dev": 6542,
                            "scores_times": [
                                "2_1365827413",
                                "1_1365828206"
                            ]
                        }
                    ]
                }
            ]
        }
    ]
}